explosig_data/__init__.py
explosig_data/categories.py
explosig_data/constants.py
explosig_data/data_source_ICGC.py
explosig_data/data_source_TCGA.py
explosig_data/genes.py
explosig_data/genomes.py
explosig_data/i_o.py
explosig_data/ssm_container.py
explosig_data/ssm_counts.py
explosig_data/ssm_extended.py
explosig_data/utils.py
explosig_data/snakefiles/genes/human.smk
explosig_data/snakefiles/genomes/human.smk
explosig_data-0.0.5.dist-info/LICENSE
explosig_data-0.0.5.dist-info/METADATA
explosig_data-0.0.5.dist-info/WHEEL
explosig_data-0.0.5.dist-info/top_level.txt
explosig_data-0.0.5.dist-info/RECORD
