Metadata-Version: 2.1
Name: explosig-data
Version: 0.0.5
Summary: Process mutation data into standard formats originally developed for the ExploSig family of tools
Home-page: https://github.com/lrgr/explosig-data
Author: Leiserson Research Group
License: UNKNOWN
Platform: UNKNOWN
Classifier: Programming Language :: Python :: 3
Classifier: License :: OSI Approved :: MIT License
Classifier: Operating System :: OS Independent
Requires-Python: >=3.6
Requires-Dist: requests (>=2.22.0)
Requires-Dist: pandas (>=0.25.1)
Requires-Dist: numpy (>=1.17.0)
Requires-Dist: snakemake (>=5.3)
Requires-Dist: biopython (>=1.75)
Requires-Dist: twobitreader (>=3.1)
Requires-Dist: tqdm (>=4.39.0)
